recpulse/__init__.py
recpulse/activations.py
recpulse/differentiated_activations.py
recpulse/differentiated_losses.py
recpulse/dtypes.py
recpulse/layers.py
recpulse/losses.py
recpulse/metrics.py
recpulse/models.py
recpulse/np_dtypes.py
tests/__init__.py
tests/test_activations.py
tests/test_layers.py
tests/test_losses.py
tests/test_sequential.py
recpulse-0.0.14.dist-info/METADATA
recpulse-0.0.14.dist-info/WHEEL
recpulse-0.0.14.dist-info/top_level.txt
recpulse-0.0.14.dist-info/RECORD
