Metadata-Version: 2.1
Name: recpulse
Version: 0.0.14
Summary: ML framework
Author: Maksym Petrenko
Author-email: maksym.petrenko.a@gmail.com
